aws_cognito_auth/__init__.py
aws_cognito_auth/admin.py
aws_cognito_auth/client.py
aws_cognito_auth/lambda_function.py
aws_cognito_auth/policies/README.md
aws_cognito_auth/policies/__init__.py
aws_cognito_auth/policies/cognito-identity-pool-auth-policy.json
aws_cognito_auth/policies/cognito-idp-policy.json
aws_cognito_auth/policies/dynamodb-user-isolation-policy.json
aws_cognito_auth/policies/lambda-execution-policy.json
aws_cognito_auth/policies/lambda-execution-trust-policy.json
aws_cognito_auth/policies/lambda-invoke-policy.json
aws_cognito_auth/policies/lambda-user-policy.json
aws_cognito_auth/policies/long-lived-role-trust-policy.json
aws_cognito_auth/policies/s3-access-policy.json
aws_cognito_auth/policies/s3-user-isolation-policy.json
aws_cognito_auth-0.0.7.dist-info/METADATA
aws_cognito_auth-0.0.7.dist-info/WHEEL
aws_cognito_auth-0.0.7.dist-info/entry_points.txt
aws_cognito_auth-0.0.7.dist-info/licenses/LICENSE
aws_cognito_auth-0.0.7.dist-info/RECORD
