Metadata-Version: 2.4
Name: aws-cognito-auth
Version: 0.0.7
Summary: AWS Cognito authentication CLI tool for seamless AWS CLI integration with temporary credential management.
Project-URL: Homepage, https://jiahao1553.github.io/aws-cognito-auth/
Project-URL: Repository, https://github.com/jiahao1553/aws-cognito-auth
Project-URL: Documentation, https://jiahao1553.github.io/aws-cognito-auth/
Author-email: JiaHao Tan <jiahaotan@outlook.com>
License-File: LICENSE
Keywords: authentication,aws,cli,cognito,credentials,python
Classifier: Development Status :: 5 - Production/Stable
Classifier: Environment :: Console
Classifier: Intended Audience :: Developers
Classifier: License :: OSI Approved :: MIT License
Classifier: Operating System :: OS Independent
Classifier: Programming Language :: Python
Classifier: Programming Language :: Python :: 3
Classifier: Programming Language :: Python :: 3.9
Classifier: Programming Language :: Python :: 3.10
Classifier: Programming Language :: Python :: 3.11
Classifier: Programming Language :: Python :: 3.12
Classifier: Programming Language :: Python :: 3.13
Classifier: Topic :: Software Development :: Libraries :: Python Modules
Classifier: Topic :: System :: Systems Administration :: Authentication/Directory
Classifier: Topic :: Utilities
Requires-Python: <4.0,>=3.9
Requires-Dist: boto3>=1.26.0
Requires-Dist: botocore>=1.29.0
Requires-Dist: click>=8.0.0
